Workbook

Sheet Assumptions
A1: SaaS P&L — Assumptions (Badminton Payment Bot)
A3: PRICING
A4: Price / tenant (VND/mo) | B4: 99000
A5: FX (USD->VND) | B5: 26300
A6: Price / tenant (USD/mo) | B6: =B4/B5 -> 3.7642586
A8: USAGE / TENANT / MONTH
A9: OCR images / mo | B9: 25
A10: STT commands / mo | B10: 30
A12: UNIT COST (platform pays)
A13: OCR $/image | B13: 0.002
A14: STT $/command | B14: 0.00015
A16: DERIVED
A17: Variable cost / tenant (USD/mo) | B17: =B9*B13+B10*B14 -> 0.0545
A18: Variable cost / tenant (VND/mo) | B18: =B17*B5 -> 1433.35
A19: Gross profit / tenant (USD) | B19: =B6-B17 -> 3.7097586
A21: Infra (hosting/Postgres/web/email/monitoring) = STEP cost vs tenant count;
A22: entered per-scenario on 'P&L' (blue). Web = Telegram-first nen nho (CF Pages
A23: free / gop vao service bot); chi tach phi khi muon deploy Next.js rieng.

Sheet P&L
A1: SaaS P&L by Tenant Count — 99k VND/mo, platform pays LLM/STT
A2: (figures = monthly unless noted)
A3: Metric | B3: 10 | C3: 50 | D3: 100 | E3: 500 | F3: 1000 | G3: 2000
A4: Paying tenants | B4: 10 | C4: 50 | D4: 100 | E4: 500 | F4: 1000 | G4: 2000
A5: Price / tenant (VND) | B5: =Assumptions!$B$4 -> 99000 | C5: =Assumptions!$B$4 -> 99000 | D5: =Assumptions!$B$4 -> 99000 | E5: =Assumptions!$B$4 -> 99000 | F5: =Assumptions!$B$4 -> 99000 | G5: =Assumptions!$B$4 -> 99000
A6: Revenue (VND/mo) | B6: =B4*B5 -> 990000 | C6: =C4*C5 -> 4950000 | D6: =D4*D5 -> 9900000 | E6: =E4*E5 -> 49500000 | F6: =F4*F5 -> 99000000 | G6: =G4*G5 -> 198000000
A7: Revenue (USD/mo) | B7: =B6/Assumptions!$B$5 -> 37.642586 | C7: =C6/Assumptions!$B$5 -> 188.21293 | D7: =D6/Assumptions!$B$5 -> 376.42586 | E7: =E6/Assumptions!$B$5 -> 1882.1293 | F7: =F6/Assumptions!$B$5 -> 3764.2586 | G7: =G6/Assumptions!$B$5 -> 7528.5171
A8: COSTS
A9: Variable LLM/STT (USD) | B9: =B4*Assumptions!$B$17 -> 0.545 | C9: =C4*Assumptions!$B$17 -> 2.725 | D9: =D4*Assumptions!$B$17 -> 5.45 | E9: =E4*Assumptions!$B$17 -> 27.25 | F9: =F4*Assumptions!$B$17 -> 54.5 | G9: =G4*Assumptions!$B$17 -> 109
A10: Infra: bot hosting (USD) | B10: 5 | C10: 20 | D10: 20 | E10: 45 | F10: 90 | G10: 90
A11: Infra: Postgres (USD) | B11: 0 | C11: 5 | D11: 5 | E11: 20 | F11: 50 | G11: 90
A12: Infra: web/dashboard (USD) | B12: 0 | C12: 0 | D12: 0 | E12: 5 | F12: 5 | G12: 10
A13: Infra: email (USD) | B13: 0 | C13: 0 | D13: 0 | E13: 20 | F13: 20 | G13: 35
A14: Infra: monitoring (USD) | B14: 0 | C14: 0 | D14: 0 | E14: 10 | F14: 10 | G14: 26
A15: Infra: domain (USD) | B15: 1.25 | C15: 1.25 | D15: 1.25 | E15: 1.25 | F15: 1.25 | G15: 1.25
A16: Infra subtotal (USD) | B16: =SUM(B10:B15) -> 6.25 | C16: =SUM(C10:C15) -> 26.25 | D16: =SUM(D10:D15) -> 26.25 | E16: =SUM(E10:E15) -> 101.25 | F16: =SUM(F10:F15) -> 176.25 | G16: =SUM(G10:G15) -> 252.25
A17: Total cost (USD/mo) | B17: =B9+B16 -> 6.795 | C17: =C9+C16 -> 28.975 | D17: =D9+D16 -> 31.7 | E17: =E9+E16 -> 128.5 | F17: =F9+F16 -> 230.75 | G17: =G9+G16 -> 361.25
A18: Total cost (VND/mo) | B18: =B17*Assumptions!$B$5 -> 178708.5 | C18: =C17*Assumptions!$B$5 -> 762042.5 | D18: =D17*Assumptions!$B$5 -> 833710 | E18: =E17*Assumptions!$B$5 -> 3379550 | F18: =F17*Assumptions!$B$5 -> 6068725 | G18: =G17*Assumptions!$B$5 -> 9500875
A19: Net profit (USD/mo) | B19: =B7-B17 -> 30.847586 | C19: =C7-C17 -> 159.23793 | D19: =D7-D17 -> 344.72586 | E19: =E7-E17 -> 1753.6293 | F19: =F7-F17 -> 3533.5086 | G19: =G7-G17 -> 7167.2671
A20: Net profit (VND/mo) | B20: =B6-B18 -> 811291.5 | C20: =C6-C18 -> 4187957.5 | D20: =D6-D18 -> 9066290 | E20: =E6-E18 -> 46120450 | F20: =F6-F18 -> 92931275 | G20: =G6-G18 -> 188499125
A21: Net margin % | B21: =B19/B7 -> 0.81948636 | C21: =C19/C7 -> 0.84605202 | D21: =D19/D7 -> 0.91578687 | E21: =E19/E7 -> 0.93172626 | F21: =F19/F7 -> 0.93869975 | G21: =G19/G7 -> 0.95201578
A22: Net profit (VND/year) | B22: =B20*12 -> 9735498 | C22: =C20*12 -> 50255490 | D22: =D20*12 -> 108795480 | E22: =E20*12 -> 553445400 | F22: =F20*12 -> 1115175300 | G22: =G20*12 -> 2261989500
A24: Break-even (paying tenants to cover smallest infra tier ~$6.25/mo): | B24: =6.25/(Assumptions!$B$6-Assumptions!$B$17) -> 1.6847458
